gpwebpay/__init__.py
gpwebpay/config.py
gpwebpay/gpwebpay.py
gpwebpay-0.1.4.dist-info/LICENSE
gpwebpay-0.1.4.dist-info/WHEEL
gpwebpay-0.1.4.dist-info/METADATA
gpwebpay-0.1.4.dist-info/RECORD
